{
    "name": "",
    "bpm": 139,
    "notes": [
        {
            "noteName": 2,
            "noteOctave": 4,
            "time": 6.474824905395508,
            "noteLength": 0.10791400074958801,
            "beatIndex": 15.0,
            "beatLengthIndex": 0.25
        },
        {
            "noteName": 2,
            "noteOctave": 4,
            "time": 6.906479835510254,
            "noteLength": 0.10791400074958801,
            "beatIndex": 16.0,
            "beatLengthIndex": 0.25
        },
        {
            "noteName": 4,
            "noteOctave": 4,
            "time": 8.201444625854493,
            "noteLength": 0.10791400074958801,
            "beatIndex": 19.0,
            "beatLengthIndex": 0.25
        },
        {
            "noteName": 5,
            "noteOctave": 4,
            "time": 8.633099555969239,
            "noteLength": 0.10791400074958801,
            "beatIndex": 20.0,
            "beatLengthIndex": 0.25
        },
        {
            "noteName": 4,
            "noteOctave": 4,
            "time": 9.928065299987793,
            "noteLength": 0.10791400074958801,
            "beatIndex": 23.0,
            "beatLengthIndex": 0.25
        },
        {
            "noteName": 2,
            "noteOctave": 4,
            "time": 10.359720230102539,
            "noteLength": 0.10791400074958801,
            "beatIndex": 24.0,
            "beatLengthIndex": 0.25
        },
        {
            "noteName": 0,
            "noteOctave": 4,
            "time": 11.654685020446778,
            "noteLength": 0.10791400074958801,
            "beatIndex": 27.0,
            "beatLengthIndex": 0.25
        },
        {
            "noteName": 2,
            "noteOctave": 4,
            "time": 12.086339950561524,
            "noteLength": 0.10791400074958801,
            "beatIndex": 28.0,
            "beatLengthIndex": 0.25
        },
        {
            "noteName": 4,
            "noteOctave": 5,
            "time": 13.381304740905762,
            "noteLength": 0.10791400074958801,
            "beatIndex": 31.0,
            "beatLengthIndex": 0.25
        },
        {
            "noteName": 5,
            "noteOctave": 4,
            "time": 13.812959671020508,
            "noteLength": 0.10791400074958801,
            "beatIndex": 32.0,
            "beatLengthIndex": 0.25
        },
        {
            "noteName": 4,
            "noteOctave": 4,
            "time": 15.107925415039063,
            "noteLength": 0.10791400074958801,
            "beatIndex": 35.0,
            "beatLengthIndex": 0.25
        },
        {
            "noteName": 2,
            "noteOctave": 4,
            "time": 15.539580345153809,
            "noteLength": 0.10791400074958801,
            "beatIndex": 36.0,
            "beatLengthIndex": 0.25
        },
        {
            "noteName": 0,
            "noteOctave": 4,
            "time": 16.834543228149415,
            "noteLength": 0.10791400074958801,
            "beatIndex": 39.0,
            "beatLengthIndex": 0.25
        },
        {
            "noteName": 2,
            "noteOctave": 4,
            "time": 17.266199111938478,
            "noteLength": 0.10791400074958801,
            "beatIndex": 40.0,
            "beatLengthIndex": 0.25
        },
        {
            "noteName": 4,
            "noteOctave": 4,
            "time": 18.56116485595703,
            "noteLength": 0.10791400074958801,
            "beatIndex": 43.0,
            "beatLengthIndex": 0.25
        },
        {
            "noteName": 5,
            "noteOctave": 4,
            "time": 18.992820739746095,
            "noteLength": 0.10791400074958801,
            "beatIndex": 44.0,
            "beatLengthIndex": 0.25
        },
        {
            "noteName": 5,
            "noteOctave": 4,
            "time": 19.424476623535158,
            "noteLength": 0.10791400074958801,
            "beatIndex": 45.0,
            "beatLengthIndex": 0.25
        },
        {
            "noteName": 5,
            "noteOctave": 4,
            "time": 19.856130599975587,
            "noteLength": 0.10791400074958801,
            "beatIndex": 46.0,
            "beatLengthIndex": 0.25
        },
        {
            "noteName": 5,
            "noteOctave": 5,
            "time": 20.287784576416017,
            "noteLength": 0.21582800149917603,
            "beatIndex": 47.0,
            "beatLengthIndex": 0.5
        },
        {
            "noteName": 4,
            "noteOctave": 4,
            "time": 20.719440460205079,
            "noteLength": 0.10791400074958801,
            "beatIndex": 48.0,
            "beatLengthIndex": 0.25
        },
        {
            "noteName": 4,
            "noteOctave": 4,
            "time": 21.15109634399414,
            "noteLength": 0.10791400074958801,
            "beatIndex": 49.0,
            "beatLengthIndex": 0.25
        },
        {
            "noteName": 2,
            "noteOctave": 4,
            "time": 22.014404296875,
            "noteLength": 0.10791400074958801,
            "beatIndex": 51.0,
            "beatLengthIndex": 0.25
        },
        {
            "noteName": 2,
            "noteOctave": 4,
            "time": 22.446060180664064,
            "noteLength": 0.10791400074958801,
            "beatIndex": 52.0,
            "beatLengthIndex": 0.25
        },
        {
            "noteName": 2,
            "noteOctave": 4,
            "time": 22.877716064453126,
            "noteLength": 0.10791400074958801,
            "beatIndex": 53.0,
            "beatLengthIndex": 0.25
        },
        {
            "noteName": 0,
            "noteOctave": 4,
            "time": 23.741024017333986,
            "noteLength": 0.10791400074958801,
            "beatIndex": 55.0,
            "beatLengthIndex": 0.25
        },
        {
            "noteName": 0,
            "noteOctave": 4,
            "time": 24.172679901123048,
            "noteLength": 0.10791400074958801,
            "beatIndex": 56.0,
            "beatLengthIndex": 0.25
        },
        {
            "noteName": 0,
            "noteOctave": 4,
            "time": 24.60433578491211,
            "noteLength": 0.10791400074958801,
            "beatIndex": 57.0,
            "beatLengthIndex": 0.25
        },
        {
            "noteName": 2,
            "noteOctave": 4,
            "time": 25.46764373779297,
            "noteLength": 0.10791400074958801,
            "beatIndex": 59.0,
            "beatLengthIndex": 0.25
        },
        {
            "noteName": 2,
            "noteOctave": 4,
            "time": 25.89929962158203,
            "noteLength": 0.10791400074958801,
            "beatIndex": 60.0,
            "beatLengthIndex": 0.25
        },
        {
            "noteName": 2,
            "noteOctave": 4,
            "time": 26.330955505371095,
            "noteLength": 0.10791400074958801,
            "beatIndex": 61.0,
            "beatLengthIndex": 0.25
        },
        {
            "noteName": 4,
            "noteOctave": 4,
            "time": 27.194263458251954,
            "noteLength": 0.10791400074958801,
            "beatIndex": 63.0,
            "beatLengthIndex": 0.25
        },
        {
            "noteName": 4,
            "noteOctave": 4,
            "time": 27.625919342041017,
            "noteLength": 0.10791400074958801,
            "beatIndex": 64.0,
            "beatLengthIndex": 0.25
        },
        {
            "noteName": 4,
            "noteOctave": 4,
            "time": 28.057575225830079,
            "noteLength": 0.10791400074958801,
            "beatIndex": 65.0,
            "beatLengthIndex": 0.25
        },
        {
            "noteName": 5,
            "noteOctave": 4,
            "time": 28.920883178710939,
            "noteLength": 0.10791400074958801,
            "beatIndex": 67.0,
            "beatLengthIndex": 0.25
        },
        {
            "noteName": 5,
            "noteOctave": 4,
            "time": 29.3525390625,
            "noteLength": 0.10791400074958801,
            "beatIndex": 68.0,
            "beatLengthIndex": 0.25
        },
        {
            "noteName": 5,
            "noteOctave": 4,
            "time": 29.784196853637697,
            "noteLength": 0.10791400074958801,
            "beatIndex": 69.0,
            "beatLengthIndex": 0.25
        },
        {
            "noteName": 4,
            "noteOctave": 4,
            "time": 30.647504806518556,
            "noteLength": 0.10791400074958801,
            "beatIndex": 71.0,
            "beatLengthIndex": 0.25
        },
        {
            "noteName": 4,
            "noteOctave": 4,
            "time": 31.079160690307618,
            "noteLength": 0.10791400074958801,
            "beatIndex": 72.0,
            "beatLengthIndex": 0.25
        },
        {
            "noteName": 4,
            "noteOctave": 4,
            "time": 31.51081657409668,
            "noteLength": 0.10791400074958801,
            "beatIndex": 73.0,
            "beatLengthIndex": 0.25
        },
        {
            "noteName": 2,
            "noteOctave": 4,
            "time": 32.374122619628909,
            "noteLength": 0.10791400074958801,
            "beatIndex": 75.0,
            "beatLengthIndex": 0.25
        },
        {
            "noteName": 0,
            "noteOctave": 4,
            "time": 32.80577850341797,
            "noteLength": 0.10791400074958801,
            "beatIndex": 76.0,
            "beatLengthIndex": 0.25
        },
        {
            "noteName": 2,
            "noteOctave": 4,
            "time": 33.23743438720703,
            "noteLength": 0.10791400074958801,
            "beatIndex": 77.0,
            "beatLengthIndex": 0.25
        },
        {
            "noteName": 4,
            "noteOctave": 4,
            "time": 33.66908645629883,
            "noteLength": 0.10791400074958801,
            "beatIndex": 78.0,
            "beatLengthIndex": 0.25
        },
        {
            "noteName": 5,
            "noteOctave": 5,
            "time": 34.10074234008789,
            "noteLength": 0.10791400074958801,
            "beatIndex": 79.0,
            "beatLengthIndex": 0.25
        },
        {
            "noteName": 5,
            "noteOctave": 4,
            "time": 34.53239822387695,
            "noteLength": 0.10791400074958801,
            "beatIndex": 80.0,
            "beatLengthIndex": 0.25
        },
        {
            "noteName": 4,
            "noteOctave": 4,
            "time": 35.395713806152347,
            "noteLength": 0.10791400074958801,
            "beatIndex": 82.0,
            "beatLengthIndex": 0.25
        },
        {
            "noteName": 2,
            "noteOctave": 4,
            "time": 36.2590217590332,
            "noteLength": 0.10791400074958801,
            "beatIndex": 84.0,
            "beatLengthIndex": 0.25
        },
        {
            "noteName": 0,
            "noteOctave": 4,
            "time": 37.12232971191406,
            "noteLength": 0.10791400074958801,
            "beatIndex": 86.0,
            "beatLengthIndex": 0.25
        },
        {
            "noteName": 0,
            "noteOctave": 4,
            "time": 37.98564147949219,
            "noteLength": 0.10791400074958801,
            "beatIndex": 88.0,
            "beatLengthIndex": 0.25
        },
        {
            "noteName": 2,
            "noteOctave": 4,
            "time": 38.84895324707031,
            "noteLength": 0.10791400074958801,
            "beatIndex": 90.0,
            "beatLengthIndex": 0.25
        },
        {
            "noteName": 4,
            "noteOctave": 4,
            "time": 39.71226119995117,
            "noteLength": 0.10791400074958801,
            "beatIndex": 92.0,
            "beatLengthIndex": 0.25
        },
        {
            "noteName": 5,
            "noteOctave": 4,
            "time": 40.57556915283203,
            "noteLength": 0.10791400074958801,
            "beatIndex": 94.0,
            "beatLengthIndex": 0.25
        },
        {
            "noteName": 5,
            "noteOctave": 4,
            "time": 41.438880920410159,
            "noteLength": 0.10791400074958801,
            "beatIndex": 96.0,
            "beatLengthIndex": 0.25
        },
        {
            "noteName": 4,
            "noteOctave": 4,
            "time": 42.30219268798828,
            "noteLength": 0.10791400074958801,
            "beatIndex": 98.0,
            "beatLengthIndex": 0.25
        },
        {
            "noteName": 2,
            "noteOctave": 4,
            "time": 43.16550064086914,
            "noteLength": 0.10791400074958801,
            "beatIndex": 100.0,
            "beatLengthIndex": 0.25
        },
        {
            "noteName": 0,
            "noteOctave": 4,
            "time": 44.02880859375,
            "noteLength": 0.10791400074958801,
            "beatIndex": 102.0,
            "beatLengthIndex": 0.25
        },
        {
            "noteName": 0,
            "noteOctave": 4,
            "time": 44.892120361328128,
            "noteLength": 0.10791400074958801,
            "beatIndex": 104.0,
            "beatLengthIndex": 0.25
        },
        {
            "noteName": 2,
            "noteOctave": 4,
            "time": 45.75543212890625,
            "noteLength": 0.10791400074958801,
            "beatIndex": 106.0,
            "beatLengthIndex": 0.25
        },
        {
            "noteName": 4,
            "noteOctave": 4,
            "time": 46.61874008178711,
            "noteLength": 0.10791400074958801,
            "beatIndex": 108.0,
            "beatLengthIndex": 0.25
        },
        {
            "noteName": 5,
            "noteOctave": 5,
            "time": 47.48204803466797,
            "noteLength": 0.8633099794387817,
            "beatIndex": 110.0,
            "beatLengthIndex": 2.0
        },
        {
            "noteName": 0,
            "noteOctave": 4,
            "time": 48.345359802246097,
            "noteLength": 0.21582800149917603,
            "beatIndex": 112.0,
            "beatLengthIndex": 0.5
        },
        {
            "noteName": 2,
            "noteOctave": 4,
            "time": 48.777015686035159,
            "noteLength": 0.21582800149917603,
            "beatIndex": 113.0,
            "beatLengthIndex": 0.5
        },
        {
            "noteName": 4,
            "noteOctave": 4,
            "time": 49.20867156982422,
            "noteLength": 0.21582800149917603,
            "beatIndex": 114.0,
            "beatLengthIndex": 0.5
        },
        {
            "noteName": 5,
            "noteOctave": 4,
            "time": 49.640323638916019,
            "noteLength": 0.21582800149917603,
            "beatIndex": 115.0,
            "beatLengthIndex": 0.5
        },
        {
            "noteName": 0,
            "noteOctave": 4,
            "time": 50.07197952270508,
            "noteLength": 0.21582800149917603,
            "beatIndex": 116.0,
            "beatLengthIndex": 0.5
        },
        {
            "noteName": 2,
            "noteOctave": 4,
            "time": 50.28780746459961,
            "noteLength": 0.21582700312137605,
            "beatIndex": 116.5,
            "beatLengthIndex": 0.5
        },
        {
            "noteName": 4,
            "noteOctave": 4,
            "time": 50.50363540649414,
            "noteLength": 0.21582800149917603,
            "beatIndex": 117.0,
            "beatLengthIndex": 0.5
        },
        {
            "noteName": 5,
            "noteOctave": 4,
            "time": 50.71946334838867,
            "noteLength": 0.21582700312137605,
            "beatIndex": 117.5,
            "beatLengthIndex": 0.5
        },
        {
            "noteName": 0,
            "noteOctave": 4,
            "time": 50.93528747558594,
            "noteLength": 0.21582800149917603,
            "beatIndex": 118.0,
            "beatLengthIndex": 0.5
        },
        {
            "noteName": 2,
            "noteOctave": 4,
            "time": 51.151119232177737,
            "noteLength": 0.21582700312137605,
            "beatIndex": 118.5,
            "beatLengthIndex": 0.5
        },
        {
            "noteName": 4,
            "noteOctave": 4,
            "time": 51.366943359375,
            "noteLength": 0.21582800149917603,
            "beatIndex": 119.0,
            "beatLengthIndex": 0.5
        },
        {
            "noteName": 5,
            "noteOctave": 4,
            "time": 51.58277130126953,
            "noteLength": 0.21582700312137605,
            "beatIndex": 119.5,
            "beatLengthIndex": 0.5
        },
        {
            "noteName": 0,
            "noteOctave": 4,
            "time": 53.52521896362305,
            "noteLength": 0.21582800149917603,
            "beatIndex": 124.0,
            "beatLengthIndex": 0.5
        },
        {
            "noteName": 0,
            "noteOctave": 4,
            "time": 53.95687484741211,
            "noteLength": 0.21582800149917603,
            "beatIndex": 125.0,
            "beatLengthIndex": 0.5
        },
        {
            "noteName": 0,
            "noteOctave": 4,
            "time": 54.388526916503909,
            "noteLength": 0.21582800149917603,
            "beatIndex": 126.0,
            "beatLengthIndex": 0.5
        },
        {
            "noteName": 0,
            "noteOctave": 4,
            "time": 54.82018280029297,
            "noteLength": 0.21582800149917603,
            "beatIndex": 127.0,
            "beatLengthIndex": 0.5
        },
        {
            "noteName": 2,
            "noteOctave": 4,
            "time": 55.25183868408203,
            "noteLength": 0.21582800149917603,
            "beatIndex": 128.0,
            "beatLengthIndex": 0.5
        },
        {
            "noteName": 2,
            "noteOctave": 4,
            "time": 55.683494567871097,
            "noteLength": 0.21582800149917603,
            "beatIndex": 129.0,
            "beatLengthIndex": 0.5
        },
        {
            "noteName": 2,
            "noteOctave": 4,
            "time": 56.115150451660159,
            "noteLength": 0.21582800149917603,
            "beatIndex": 130.0,
            "beatLengthIndex": 0.5
        },
        {
            "noteName": 2,
            "noteOctave": 4,
            "time": 56.54680252075195,
            "noteLength": 0.21582800149917603,
            "beatIndex": 131.0,
            "beatLengthIndex": 0.5
        },
        {
            "noteName": 4,
            "noteOctave": 4,
            "time": 56.978458404541019,
            "noteLength": 0.21582800149917603,
            "beatIndex": 132.0,
            "beatLengthIndex": 0.5
        },
        {
            "noteName": 4,
            "noteOctave": 4,
            "time": 57.41011428833008,
            "noteLength": 0.21582800149917603,
            "beatIndex": 133.0,
            "beatLengthIndex": 0.5
        },
        {
            "noteName": 4,
            "noteOctave": 4,
            "time": 57.841766357421878,
            "noteLength": 0.21582800149917603,
            "beatIndex": 134.0,
            "beatLengthIndex": 0.5
        },
        {
            "noteName": 4,
            "noteOctave": 4,
            "time": 58.27342224121094,
            "noteLength": 0.21582800149917603,
            "beatIndex": 135.0,
            "beatLengthIndex": 0.5
        },
        {
            "noteName": 5,
            "noteOctave": 4,
            "time": 58.705078125,
            "noteLength": 0.21582800149917603,
            "beatIndex": 136.0,
            "beatLengthIndex": 0.5
        },
        {
            "noteName": 5,
            "noteOctave": 4,
            "time": 59.13673782348633,
            "noteLength": 0.21582800149917603,
            "beatIndex": 137.0,
            "beatLengthIndex": 0.5
        },
        {
            "noteName": 5,
            "noteOctave": 4,
            "time": 59.56839370727539,
            "noteLength": 0.21582800149917603,
            "beatIndex": 138.0,
            "beatLengthIndex": 0.5
        },
        {
            "noteName": 5,
            "noteOctave": 4,
            "time": 60.00004577636719,
            "noteLength": 0.21582800149917603,
            "beatIndex": 139.0,
            "beatLengthIndex": 0.5
        },
        {
            "noteName": 4,
            "noteOctave": 4,
            "time": 60.43170166015625,
            "noteLength": 0.21582800149917603,
            "beatIndex": 140.0,
            "beatLengthIndex": 0.5
        },
        {
            "noteName": 4,
            "noteOctave": 4,
            "time": 60.86335754394531,
            "noteLength": 0.21582800149917603,
            "beatIndex": 141.0,
            "beatLengthIndex": 0.5
        },
        {
            "noteName": 4,
            "noteOctave": 4,
            "time": 61.29500961303711,
            "noteLength": 0.21582800149917603,
            "beatIndex": 142.0,
            "beatLengthIndex": 0.5
        },
        {
            "noteName": 4,
            "noteOctave": 4,
            "time": 61.72666549682617,
            "noteLength": 0.21582800149917603,
            "beatIndex": 143.0,
            "beatLengthIndex": 0.5
        },
        {
            "noteName": 2,
            "noteOctave": 4,
            "time": 62.158321380615237,
            "noteLength": 0.21582800149917603,
            "beatIndex": 144.0,
            "beatLengthIndex": 0.5
        },
        {
            "noteName": 2,
            "noteOctave": 4,
            "time": 62.5899772644043,
            "noteLength": 0.21582800149917603,
            "beatIndex": 145.0,
            "beatLengthIndex": 0.5
        },
        {
            "noteName": 2,
            "noteOctave": 4,
            "time": 63.02163314819336,
            "noteLength": 0.21582800149917603,
            "beatIndex": 146.0,
            "beatLengthIndex": 0.5
        },
        {
            "noteName": 2,
            "noteOctave": 4,
            "time": 63.453285217285159,
            "noteLength": 0.21582800149917603,
            "beatIndex": 147.0,
            "beatLengthIndex": 0.5
        },
        {
            "noteName": 0,
            "noteOctave": 4,
            "time": 63.88494110107422,
            "noteLength": 0.21582800149917603,
            "beatIndex": 148.0,
            "beatLengthIndex": 0.5
        },
        {
            "noteName": 2,
            "noteOctave": 4,
            "time": 64.74824523925781,
            "noteLength": 0.21582800149917603,
            "beatIndex": 150.0,
            "beatLengthIndex": 0.5
        },
        {
            "noteName": 4,
            "noteOctave": 4,
            "time": 65.61155700683594,
            "noteLength": 0.21582800149917603,
            "beatIndex": 152.0,
            "beatLengthIndex": 0.5
        },
        {
            "noteName": 5,
            "noteOctave": 4,
            "time": 66.47486877441406,
            "noteLength": 0.21582800149917603,
            "beatIndex": 154.0,
            "beatLengthIndex": 0.5
        },
        {
            "noteName": 5,
            "noteOctave": 5,
            "time": 66.90652465820313,
            "noteLength": 0.43165498971939089,
            "beatIndex": 155.0,
            "beatLengthIndex": 1.0
        },
        {
            "noteName": 5,
            "noteOctave": 4,
            "time": 67.33817291259766,
            "noteLength": 0.21582800149917603,
            "beatIndex": 156.0,
            "beatLengthIndex": 0.5
        },
        {
            "noteName": 5,
            "noteOctave": 4,
            "time": 67.76982879638672,
            "noteLength": 0.21582800149917603,
            "beatIndex": 157.0,
            "beatLengthIndex": 0.5
        },
        {
            "noteName": 5,
            "noteOctave": 4,
            "time": 68.20148468017578,
            "noteLength": 0.21582800149917603,
            "beatIndex": 158.0,
            "beatLengthIndex": 0.5
        },
        {
            "noteName": 4,
            "noteOctave": 4,
            "time": 68.63314056396485,
            "noteLength": 0.21582800149917603,
            "beatIndex": 159.0,
            "beatLengthIndex": 0.5
        },
        {
            "noteName": 2,
            "noteOctave": 4,
            "time": 69.0647964477539,
            "noteLength": 0.21582800149917603,
            "beatIndex": 160.0,
            "beatLengthIndex": 0.5
        },
        {
            "noteName": 2,
            "noteOctave": 4,
            "time": 69.49645233154297,
            "noteLength": 0.21582800149917603,
            "beatIndex": 161.0,
            "beatLengthIndex": 0.5
        },
        {
            "noteName": 2,
            "noteOctave": 4,
            "time": 69.92810821533203,
            "noteLength": 0.21582800149917603,
            "beatIndex": 162.0,
            "beatLengthIndex": 0.5
        },
        {
            "noteName": 0,
            "noteOctave": 4,
            "time": 70.35977172851563,
            "noteLength": 0.21582800149917603,
            "beatIndex": 163.0,
            "beatLengthIndex": 0.5
        },
        {
            "noteName": 0,
            "noteOctave": 4,
            "time": 70.79142761230469,
            "noteLength": 0.21582800149917603,
            "beatIndex": 164.0,
            "beatLengthIndex": 0.5
        },
        {
            "noteName": 0,
            "noteOctave": 4,
            "time": 71.22306823730469,
            "noteLength": 0.21582800149917603,
            "beatIndex": 165.0,
            "beatLengthIndex": 0.5
        },
        {
            "noteName": 0,
            "noteOctave": 4,
            "time": 71.65473175048828,
            "noteLength": 0.21582800149917603,
            "beatIndex": 166.0,
            "beatLengthIndex": 0.5
        },
        {
            "noteName": 2,
            "noteOctave": 4,
            "time": 72.08638763427735,
            "noteLength": 0.21582800149917603,
            "beatIndex": 167.0,
            "beatLengthIndex": 0.5
        },
        {
            "noteName": 4,
            "noteOctave": 4,
            "time": 72.5180435180664,
            "noteLength": 0.21582800149917603,
            "beatIndex": 168.0,
            "beatLengthIndex": 0.5
        },
        {
            "noteName": 4,
            "noteOctave": 4,
            "time": 72.94969940185547,
            "noteLength": 0.21582800149917603,
            "beatIndex": 169.0,
            "beatLengthIndex": 0.5
        },
        {
            "noteName": 5,
            "noteOctave": 4,
            "time": 73.38135528564453,
            "noteLength": 0.21582800149917603,
            "beatIndex": 170.0,
            "beatLengthIndex": 0.5
        },
        {
            "noteName": 5,
            "noteOctave": 5,
            "time": 73.8130111694336,
            "noteLength": 0.10791400074958801,
            "beatIndex": 171.0,
            "beatLengthIndex": 0.25
        },
        {
            "noteName": 5,
            "noteOctave": 4,
            "time": 74.24465942382813,
            "noteLength": 0.21582800149917603,
            "beatIndex": 172.0,
            "beatLengthIndex": 0.5
        },
        {
            "noteName": 5,
            "noteOctave": 4,
            "time": 74.67631530761719,
            "noteLength": 0.21582800149917603,
            "beatIndex": 173.0,
            "beatLengthIndex": 0.5
        },
        {
            "noteName": 5,
            "noteOctave": 4,
            "time": 75.10797119140625,
            "noteLength": 0.21582800149917603,
            "beatIndex": 174.0,
            "beatLengthIndex": 0.5
        },
        {
            "noteName": 4,
            "noteOctave": 4,
            "time": 75.53962707519531,
            "noteLength": 0.21582800149917603,
            "beatIndex": 175.0,
            "beatLengthIndex": 0.5
        },
        {
            "noteName": 2,
            "noteOctave": 4,
            "time": 75.97128295898438,
            "noteLength": 0.21582800149917603,
            "beatIndex": 176.0,
            "beatLengthIndex": 0.5
        },
        {
            "noteName": 2,
            "noteOctave": 4,
            "time": 76.40293884277344,
            "noteLength": 0.21582800149917603,
            "beatIndex": 177.0,
            "beatLengthIndex": 0.5
        },
        {
            "noteName": 2,
            "noteOctave": 4,
            "time": 76.8345947265625,
            "noteLength": 0.21582800149917603,
            "beatIndex": 178.0,
            "beatLengthIndex": 0.5
        },
        {
            "noteName": 0,
            "noteOctave": 4,
            "time": 77.26625061035156,
            "noteLength": 0.21582800149917603,
            "beatIndex": 179.0,
            "beatLengthIndex": 0.5
        },
        {
            "noteName": 0,
            "noteOctave": 4,
            "time": 77.69790649414063,
            "noteLength": 0.21582800149917603,
            "beatIndex": 180.0,
            "beatLengthIndex": 0.5
        },
        {
            "noteName": 0,
            "noteOctave": 4,
            "time": 78.12955474853516,
            "noteLength": 0.21582800149917603,
            "beatIndex": 181.0,
            "beatLengthIndex": 0.5
        },
        {
            "noteName": 0,
            "noteOctave": 4,
            "time": 78.56121063232422,
            "noteLength": 0.21582800149917603,
            "beatIndex": 182.0,
            "beatLengthIndex": 0.5
        },
        {
            "noteName": 2,
            "noteOctave": 4,
            "time": 78.99286651611328,
            "noteLength": 0.21582800149917603,
            "beatIndex": 183.0,
            "beatLengthIndex": 0.5
        },
        {
            "noteName": 4,
            "noteOctave": 4,
            "time": 79.42452239990235,
            "noteLength": 0.21582800149917603,
            "beatIndex": 184.0,
            "beatLengthIndex": 0.5
        },
        {
            "noteName": 4,
            "noteOctave": 4,
            "time": 79.8561782836914,
            "noteLength": 0.21582800149917603,
            "beatIndex": 185.0,
            "beatLengthIndex": 0.5
        },
        {
            "noteName": 4,
            "noteOctave": 4,
            "time": 80.28783416748047,
            "noteLength": 0.21582800149917603,
            "beatIndex": 186.0,
            "beatLengthIndex": 0.5
        },
        {
            "noteName": 4,
            "noteOctave": 5,
            "time": 80.71949005126953,
            "noteLength": 0.21582800149917603,
            "beatIndex": 187.0,
            "beatLengthIndex": 0.5
        },
        {
            "noteName": 4,
            "noteOctave": 4,
            "time": 81.15113830566406,
            "noteLength": 0.21582800149917603,
            "beatIndex": 188.0,
            "beatLengthIndex": 0.5
        },
        {
            "noteName": 4,
            "noteOctave": 4,
            "time": 84.1727294921875,
            "noteLength": 0.21582800149917603,
            "beatIndex": 195.0,
            "beatLengthIndex": 0.5
        },
        {
            "noteName": 4,
            "noteOctave": 4,
            "time": 84.60438537597656,
            "noteLength": 0.21582800149917603,
            "beatIndex": 196.0,
            "beatLengthIndex": 0.5
        },
        {
            "noteName": 2,
            "noteOctave": 4,
            "time": 85.89934539794922,
            "noteLength": 0.21582800149917603,
            "beatIndex": 199.0,
            "beatLengthIndex": 0.5
        },
        {
            "noteName": 0,
            "noteOctave": 4,
            "time": 86.33100128173828,
            "noteLength": 0.21582800149917603,
            "beatIndex": 200.0,
            "beatLengthIndex": 0.5
        },
        {
            "noteName": 0,
            "noteOctave": 4,
            "time": 87.62596893310547,
            "noteLength": 0.21582800149917603,
            "beatIndex": 203.0,
            "beatLengthIndex": 0.5
        },
        {
            "noteName": 2,
            "noteOctave": 4,
            "time": 88.0576171875,
            "noteLength": 0.21582800149917603,
            "beatIndex": 204.0,
            "beatLengthIndex": 0.5
        },
        {
            "noteName": 2,
            "noteOctave": 4,
            "time": 89.35258483886719,
            "noteLength": 0.21582800149917603,
            "beatIndex": 207.0,
            "beatLengthIndex": 0.5
        },
        {
            "noteName": 4,
            "noteOctave": 4,
            "time": 89.78424072265625,
            "noteLength": 0.21582800149917603,
            "beatIndex": 208.0,
            "beatLengthIndex": 0.5
        },
        {
            "noteName": 4,
            "noteOctave": 5,
            "time": 91.07920837402344,
            "noteLength": 0.21582800149917603,
            "beatIndex": 211.0,
            "beatLengthIndex": 0.5
        },
        {
            "noteName": 4,
            "noteOctave": 4,
            "time": 91.5108642578125,
            "noteLength": 0.21582800149917603,
            "beatIndex": 212.0,
            "beatLengthIndex": 0.5
        },
        {
            "noteName": 4,
            "noteOctave": 4,
            "time": 92.3741683959961,
            "noteLength": 0.21582800149917603,
            "beatIndex": 214.0,
            "beatLengthIndex": 0.5
        },
        {
            "noteName": 2,
            "noteOctave": 4,
            "time": 93.23748016357422,
            "noteLength": 0.21582800149917603,
            "beatIndex": 216.0,
            "beatLengthIndex": 0.5
        },
        {
            "noteName": 2,
            "noteOctave": 4,
            "time": 94.10079193115235,
            "noteLength": 0.21582800149917603,
            "beatIndex": 218.0,
            "beatLengthIndex": 0.5
        },
        {
            "noteName": 2,
            "noteOctave": 5,
            "time": 94.5324478149414,
            "noteLength": 0.43165498971939089,
            "beatIndex": 219.0,
            "beatLengthIndex": 1.0
        },
        {
            "noteName": 2,
            "noteOctave": 4,
            "time": 94.96409606933594,
            "noteLength": 0.21582800149917603,
            "beatIndex": 220.0,
            "beatLengthIndex": 0.5
        },
        {
            "noteName": 0,
            "noteOctave": 4,
            "time": 95.395751953125,
            "noteLength": 0.21582800149917603,
            "beatIndex": 221.0,
            "beatLengthIndex": 0.5
        },
        {
            "noteName": 2,
            "noteOctave": 4,
            "time": 95.82740783691406,
            "noteLength": 0.21582800149917603,
            "beatIndex": 222.0,
            "beatLengthIndex": 0.5
        },
        {
            "noteName": 4,
            "noteOctave": 4,
            "time": 96.25906372070313,
            "noteLength": 0.21582800149917603,
            "beatIndex": 223.0,
            "beatLengthIndex": 0.5
        },
        {
            "noteName": 5,
            "noteOctave": 4,
            "time": 96.69071960449219,
            "noteLength": 0.21582800149917603,
            "beatIndex": 224.0,
            "beatLengthIndex": 0.5
        },
        {
            "noteName": 5,
            "noteOctave": 4,
            "time": 98.41734313964844,
            "noteLength": 0.21582800149917603,
            "beatIndex": 228.0,
            "beatLengthIndex": 0.5
        },
        {
            "noteName": 5,
            "noteOctave": 4,
            "time": 99.4964828491211,
            "noteLength": 0.21582700312137605,
            "beatIndex": 230.5,
            "beatLengthIndex": 0.5
        },
        {
            "noteName": 5,
            "noteOctave": 4,
            "time": 99.92813873291016,
            "noteLength": 0.21582700312137605,
            "beatIndex": 231.5,
            "beatLengthIndex": 0.5
        },
        {
            "noteName": 4,
            "noteOctave": 4,
            "time": 101.22309875488281,
            "noteLength": 0.21582700312137605,
            "beatIndex": 234.5,
            "beatLengthIndex": 0.5
        },
        {
            "noteName": 4,
            "noteOctave": 4,
            "time": 101.65475463867188,
            "noteLength": 0.21582700312137605,
            "beatIndex": 235.5,
            "beatLengthIndex": 0.5
        },
        {
            "noteName": 2,
            "noteOctave": 4,
            "time": 102.94972229003906,
            "noteLength": 0.21582700312137605,
            "beatIndex": 238.5,
            "beatLengthIndex": 0.5
        },
        {
            "noteName": 2,
            "noteOctave": 4,
            "time": 103.38137817382813,
            "noteLength": 0.21582700312137605,
            "beatIndex": 239.5,
            "beatLengthIndex": 0.5
        },
        {
            "noteName": 0,
            "noteOctave": 4,
            "time": 104.46051025390625,
            "noteLength": 0.21582800149917603,
            "beatIndex": 242.0,
            "beatLengthIndex": 0.5
        },
        {
            "noteName": 0,
            "noteOctave": 5,
            "time": 104.89216613769531,
            "noteLength": 0.10791400074958801,
            "beatIndex": 243.0,
            "beatLengthIndex": 0.25
        },
        {
            "noteName": 2,
            "noteOctave": 4,
            "time": 105.32382202148438,
            "noteLength": 0.21582800149917603,
            "beatIndex": 244.0,
            "beatLengthIndex": 0.5
        },
        {
            "noteName": 2,
            "noteOctave": 4,
            "time": 105.7554702758789,
            "noteLength": 0.21582800149917603,
            "beatIndex": 245.0,
            "beatLengthIndex": 0.5
        },
        {
            "noteName": 4,
            "noteOctave": 4,
            "time": 106.40296173095703,
            "noteLength": 0.21582700312137605,
            "beatIndex": 246.5,
            "beatLengthIndex": 0.5
        },
        {
            "noteName": 4,
            "noteOctave": 4,
            "time": 106.8346176147461,
            "noteLength": 0.21582700312137605,
            "beatIndex": 247.5,
            "beatLengthIndex": 0.5
        },
        {
            "noteName": 4,
            "noteOctave": 4,
            "time": 107.91374969482422,
            "noteLength": 0.21582800149917603,
            "beatIndex": 250.0,
            "beatLengthIndex": 0.5
        },
        {
            "noteName": 4,
            "noteOctave": 4,
            "time": 108.77705383300781,
            "noteLength": 0.21582800149917603,
            "beatIndex": 252.0,
            "beatLengthIndex": 0.5
        },
        {
            "noteName": 4,
            "noteOctave": 4,
            "time": 109.64036560058594,
            "noteLength": 0.21582800149917603,
            "beatIndex": 254.0,
            "beatLengthIndex": 0.5
        },
        {
            "noteName": 5,
            "noteOctave": 4,
            "time": 110.50367736816406,
            "noteLength": 0.21582800149917603,
            "beatIndex": 256.0,
            "beatLengthIndex": 0.5
        },
        {
            "noteName": 4,
            "noteOctave": 4,
            "time": 110.93533325195313,
            "noteLength": 0.21582800149917603,
            "beatIndex": 257.0,
            "beatLengthIndex": 0.5
        },
        {
            "noteName": 2,
            "noteOctave": 4,
            "time": 111.36698913574219,
            "noteLength": 0.21582800149917603,
            "beatIndex": 258.0,
            "beatLengthIndex": 0.5
        },
        {
            "noteName": 0,
            "noteOctave": 5,
            "time": 111.79864501953125,
            "noteLength": 0.43165498971939089,
            "beatIndex": 259.0,
            "beatLengthIndex": 1.0
        },
        {
            "noteName": 0,
            "noteOctave": 4,
            "time": 112.23030090332031,
            "noteLength": 0.21582800149917603,
            "beatIndex": 260.0,
            "beatLengthIndex": 0.5
        },
        {
            "noteName": 0,
            "noteOctave": 4,
            "time": 112.66194915771485,
            "noteLength": 0.21582800149917603,
            "beatIndex": 261.0,
            "beatLengthIndex": 0.5
        },
        {
            "noteName": 0,
            "noteOctave": 4,
            "time": 113.0936050415039,
            "noteLength": 0.21582800149917603,
            "beatIndex": 262.0,
            "beatLengthIndex": 0.5
        },
        {
            "noteName": 2,
            "noteOctave": 4,
            "time": 113.52526092529297,
            "noteLength": 0.21582800149917603,
            "beatIndex": 263.0,
            "beatLengthIndex": 0.5
        },
        {
            "noteName": 4,
            "noteOctave": 4,
            "time": 113.95691680908203,
            "noteLength": 0.21582800149917603,
            "beatIndex": 264.0,
            "beatLengthIndex": 0.5
        },
        {
            "noteName": 4,
            "noteOctave": 4,
            "time": 114.3885726928711,
            "noteLength": 0.21582800149917603,
            "beatIndex": 265.0,
            "beatLengthIndex": 0.5
        },
        {
            "noteName": 4,
            "noteOctave": 4,
            "time": 114.82022857666016,
            "noteLength": 0.21582800149917603,
            "beatIndex": 266.0,
            "beatLengthIndex": 0.5
        },
        {
            "noteName": 5,
            "noteOctave": 4,
            "time": 115.25188446044922,
            "noteLength": 0.21582800149917603,
            "beatIndex": 267.0,
            "beatLengthIndex": 0.5
        },
        {
            "noteName": 5,
            "noteOctave": 4,
            "time": 115.68353271484375,
            "noteLength": 0.21582800149917603,
            "beatIndex": 268.0,
            "beatLengthIndex": 0.5
        },
        {
            "noteName": 5,
            "noteOctave": 4,
            "time": 116.11518859863281,
            "noteLength": 0.21582800149917603,
            "beatIndex": 269.0,
            "beatLengthIndex": 0.5
        },
        {
            "noteName": 5,
            "noteOctave": 4,
            "time": 116.54684448242188,
            "noteLength": 0.21582800149917603,
            "beatIndex": 270.0,
            "beatLengthIndex": 0.5
        },
        {
            "noteName": 4,
            "noteOctave": 4,
            "time": 116.97850036621094,
            "noteLength": 0.21582800149917603,
            "beatIndex": 271.0,
            "beatLengthIndex": 0.5
        },
        {
            "noteName": 2,
            "noteOctave": 4,
            "time": 117.41015625,
            "noteLength": 0.21582800149917603,
            "beatIndex": 272.0,
            "beatLengthIndex": 0.5
        },
        {
            "noteName": 2,
            "noteOctave": 4,
            "time": 117.8418197631836,
            "noteLength": 0.21582800149917603,
            "beatIndex": 273.0,
            "beatLengthIndex": 0.5
        },
        {
            "noteName": 2,
            "noteOctave": 4,
            "time": 118.27347564697266,
            "noteLength": 0.21582800149917603,
            "beatIndex": 274.0,
            "beatLengthIndex": 0.5
        },
        {
            "noteName": 0,
            "noteOctave": 4,
            "time": 118.70513153076172,
            "noteLength": 0.21582800149917603,
            "beatIndex": 275.0,
            "beatLengthIndex": 0.5
        },
        {
            "noteName": 0,
            "noteOctave": 4,
            "time": 119.13678741455078,
            "noteLength": 0.21582800149917603,
            "beatIndex": 276.0,
            "beatLengthIndex": 0.5
        },
        {
            "noteName": 0,
            "noteOctave": 4,
            "time": 119.56843566894531,
            "noteLength": 0.21582800149917603,
            "beatIndex": 277.0,
            "beatLengthIndex": 0.5
        },
        {
            "noteName": 0,
            "noteOctave": 4,
            "time": 120.00009155273438,
            "noteLength": 0.21582800149917603,
            "beatIndex": 278.0,
            "beatLengthIndex": 0.5
        },
        {
            "noteName": 2,
            "noteOctave": 4,
            "time": 120.43174743652344,
            "noteLength": 0.21582800149917603,
            "beatIndex": 279.0,
            "beatLengthIndex": 0.5
        },
        {
            "noteName": 4,
            "noteOctave": 4,
            "time": 120.8634033203125,
            "noteLength": 0.21582800149917603,
            "beatIndex": 280.0,
            "beatLengthIndex": 0.5
        },
        {
            "noteName": 4,
            "noteOctave": 4,
            "time": 121.29505920410156,
            "noteLength": 0.21582800149917603,
            "beatIndex": 281.0,
            "beatLengthIndex": 0.5
        },
        {
            "noteName": 4,
            "noteOctave": 4,
            "time": 121.72671508789063,
            "noteLength": 0.21582800149917603,
            "beatIndex": 282.0,
            "beatLengthIndex": 0.5
        },
        {
            "noteName": 5,
            "noteOctave": 4,
            "time": 122.15837097167969,
            "noteLength": 0.21582800149917603,
            "beatIndex": 283.0,
            "beatLengthIndex": 0.5
        },
        {
            "noteName": 5,
            "noteOctave": 4,
            "time": 122.59001922607422,
            "noteLength": 0.21582800149917603,
            "beatIndex": 284.0,
            "beatLengthIndex": 0.5
        },
        {
            "noteName": 5,
            "noteOctave": 4,
            "time": 123.02167510986328,
            "noteLength": 0.21582800149917603,
            "beatIndex": 285.0,
            "beatLengthIndex": 0.5
        },
        {
            "noteName": 5,
            "noteOctave": 4,
            "time": 123.45333099365235,
            "noteLength": 0.21582800149917603,
            "beatIndex": 286.0,
            "beatLengthIndex": 0.5
        },
        {
            "noteName": 4,
            "noteOctave": 4,
            "time": 123.8849868774414,
            "noteLength": 0.21582800149917603,
            "beatIndex": 287.0,
            "beatLengthIndex": 0.5
        },
        {
            "noteName": 4,
            "noteOctave": 4,
            "time": 124.31664276123047,
            "noteLength": 0.21582800149917603,
            "beatIndex": 288.0,
            "beatLengthIndex": 0.5
        },
        {
            "noteName": 4,
            "noteOctave": 4,
            "time": 124.74829864501953,
            "noteLength": 0.21582800149917603,
            "beatIndex": 289.0,
            "beatLengthIndex": 0.5
        },
        {
            "noteName": 4,
            "noteOctave": 4,
            "time": 125.1799545288086,
            "noteLength": 0.21582800149917603,
            "beatIndex": 290.0,
            "beatLengthIndex": 0.5
        },
        {
            "noteName": 4,
            "noteOctave": 5,
            "time": 125.61161041259766,
            "noteLength": 0.21582800149917603,
            "beatIndex": 291.0,
            "beatLengthIndex": 0.5
        },
        {
            "noteName": 4,
            "noteOctave": 4,
            "time": 126.04326629638672,
            "noteLength": 0.21582800149917603,
            "beatIndex": 292.0,
            "beatLengthIndex": 0.5
        },
        {
            "noteName": 5,
            "noteOctave": 4,
            "time": 126.90657043457031,
            "noteLength": 0.21582800149917603,
            "beatIndex": 294.0,
            "beatLengthIndex": 0.5
        },
        {
            "noteName": 4,
            "noteOctave": 4,
            "time": 127.76988220214844,
            "noteLength": 0.21582800149917603,
            "beatIndex": 296.0,
            "beatLengthIndex": 0.5
        },
        {
            "noteName": 2,
            "noteOctave": 4,
            "time": 128.63319396972657,
            "noteLength": 0.21582800149917603,
            "beatIndex": 298.0,
            "beatLengthIndex": 0.5
        },
        {
            "noteName": 0,
            "noteOctave": 4,
            "time": 129.49649047851563,
            "noteLength": 0.21582800149917603,
            "beatIndex": 300.0,
            "beatLengthIndex": 0.5
        },
        {
            "noteName": 2,
            "noteOctave": 4,
            "time": 130.35980224609376,
            "noteLength": 0.21582800149917603,
            "beatIndex": 302.0,
            "beatLengthIndex": 0.5
        },
        {
            "noteName": 4,
            "noteOctave": 4,
            "time": 131.22311401367188,
            "noteLength": 0.21582800149917603,
            "beatIndex": 304.0,
            "beatLengthIndex": 0.5
        },
        {
            "noteName": 5,
            "noteOctave": 4,
            "time": 132.08642578125,
            "noteLength": 0.21582800149917603,
            "beatIndex": 306.0,
            "beatLengthIndex": 0.5
        }
    ]
}